support_resistance_line/__init__.py
support_resistance_line/support_resistance_line.py
support_resistance_line-0.0.7.dist-info/LICENSE
support_resistance_line-0.0.7.dist-info/METADATA
support_resistance_line-0.0.7.dist-info/WHEEL
support_resistance_line-0.0.7.dist-info/top_level.txt
support_resistance_line-0.0.7.dist-info/RECORD
