Metadata-Version: 2.1
Name: support-resistance-line
Version: 0.0.7
Summary: A well-tuned algorithm to generate & draw support/resistance line on time series. 根据时间序列自动生成支撑线压力线
Home-page: https://github.com/WestXu/support_resistance_line
Author: WestXu
Author-email: xu-lai-xi@qq.com
License: MIT
Platform: UNKNOWN
Classifier: License :: OSI Approved :: MIT License
Classifier: Operating System :: OS Independent
Classifier: Programming Language :: Python
Classifier: Programming Language :: Python :: 3.6
Classifier: Programming Language :: Python :: 3.7
Classifier: Programming Language :: Python :: 3.8
Classifier: Programming Language :: Python :: 3 :: Only
Classifier: Topic :: Software Development :: Libraries :: Python Modules
Requires-Python: >=3.6
Requires-Dist: matplotlib
Requires-Dist: numpy
Requires-Dist: pandas
Requires-Dist: sklearn
Requires-Dist: lazy-object-proxy
